mkdocs_frontmatter_url/__init__.py
mkdocs_frontmatter_url/plugin.py
mkdocs_frontmatter_url-0.1.2.dist-info/METADATA
mkdocs_frontmatter_url-0.1.2.dist-info/WHEEL
mkdocs_frontmatter_url-0.1.2.dist-info/entry_points.txt
mkdocs_frontmatter_url-0.1.2.dist-info/licenses/LICENSE
mkdocs_frontmatter_url-0.1.2.dist-info/RECORD
