Metadata-Version: 2.3
Name: mkdocs-frontmatter-url
Version: 0.1.2
Summary: A MKDocs plugin that generates a button for a URL defined in the frontmatter
Project-URL: Repository, https://github.com/JensPenny/mkdocs-frontmatter-url.git
Author-email: Jens Penny <jens.penny+pypi@gmail.com>
License-File: LICENSE
Keywords: frontmatter,mkdocs,plugin,url
Classifier: Development Status :: 3 - Alpha
Classifier: License :: OSI Approved :: MIT License
Classifier: Operating System :: OS Independent
Classifier: Programming Language :: Python :: 3 :: Only
Requires-Python: >=3.8
Requires-Dist: mkdocs
Provides-Extra: test
Requires-Dist: pytest; extra == 'test'
